README.rst
heat.py
setup.py
py_heat_magic.egg-info/PKG-INFO
py_heat_magic.egg-info/SOURCES.txt
py_heat_magic.egg-info/dependency_links.txt
py_heat_magic.egg-info/requires.txt
py_heat_magic.egg-info/top_level.txt