Metadata-Version: 1.1
Name: py-heat-magic
Version: 0.0.2
Summary: py-heat as IPython magic
Home-page: https://github.com/csurfer/pyheatmagic
Author: Vishwas B Sharma
Author-email: sharma.vishwas88@gmail.com
License: MIT
Keywords: heatmap matplotlib profiling python IPython
Platform: UNKNOWN
Classifier: Intended Audience :: Developers
Classifier: Intended Audience :: Education
Classifier: License :: OSI Approved :: MIT License
Classifier: Development Status :: 3 - Alpha
Classifier: Operating System :: POSIX
Classifier: Programming Language :: Python :: 2.7
Classifier: Programming Language :: Python :: 3.4
Classifier: Programming Language :: Python :: 3.5
Classifier: Programming Language :: Python :: 3.6
Classifier: Topic :: Software Development :: Build Tools
Classifier: Topic :: Software Development :: Libraries :: Python Modules
